fps_channels/__init__.py
fps_channels/abs_channel.py
fps_channels/async_channel.py
fps_channels/channel.py
fps_channels/exceptions.py
fps_channels/helpers.py
fps_channels-1.4.dist-info/METADATA
fps_channels-1.4.dist-info/WHEEL
fps_channels-1.4.dist-info/top_level.txt
fps_channels-1.4.dist-info/RECORD
