Metadata-Version: 2.1
Name: fps_channels
Version: 1.4
Requires-Dist: pandas ~=2.1.3
Requires-Dist: dataframe-image ~=0.2.3
Requires-Dist: tenacity ~=8.2.3
Requires-Dist: lxml ~=5.1.0
Requires-Dist: openpyxl ~=3.1.2
Requires-Dist: aiohttp ~=3.9.5
Requires-Dist: requests ~=2.32.3
